README.md
setup.cfg
setup.py
twodeploy/__init__.py
twodeploy/config.py
twodeploy/instance.py
twodeploy/logger.py
twodeploy/manager.py
twodeploy/nginx.py
twodeploy/utils.py
twodeploy.egg-info/PKG-INFO
twodeploy.egg-info/SOURCES.txt
twodeploy.egg-info/dependency_links.txt
twodeploy.egg-info/not-zip-safe
twodeploy.egg-info/requires.txt
twodeploy.egg-info/top_level.txt
twodeploy/helpers/__init__.py
twodeploy/helpers/instance.py
twodeploy/scripts/__init__.py
twodeploy/scripts/shred/__init__.py
twodeploy/template/__init__.py
twodeploy/template/utils.py
twodeploy/template/Build/__init__.py
twodeploy/template/Dockerfile - depr/__init__.py
twodeploy/template/Nginxt/__init__.py
twodeploy/template/Production/__init__.py