Metadata-Version: 2.1
Name: twodeploy
Version: 0.1.15
Summary: Deploying Package
Home-page: UNKNOWN
License: UNKNOWN
Platform: UNKNOWN
